Patche/__init__.py
Patche/__main__.py
Patche/app.py
Patche/commands/apply.py
Patche/commands/help.py
Patche/commands/show.py
Patche/config.py
Patche/model.py
Patche/utils/common.py
Patche/utils/parse.py
Patche/utils/resolve.py
patche-0.0.1.dist-info/METADATA
patche-0.0.1.dist-info/WHEEL
patche-0.0.1.dist-info/entry_points.txt
patche-0.0.1.dist-info/licenses/LICENSE
patche-0.0.1.dist-info/RECORD
