Metadata-Version: 2.1
Name: Patche
Version: 0.0.1
Summary: Modern Patch in Python
Author-Email: jingfelix <jingfelix@outlook.com>
License: MIT
Requires-Python: >=3.10
Requires-Dist: typer[all]>=0.9.0
Requires-Dist: pydantic>=2.5.3
Requires-Dist: pydantic-settings>=2.2.1
Requires-Dist: cscopy>=0.0.1
Requires-Dist: whatthepatch-pydantic==1.0.6a1
Requires-Dist: structlog>=24.2.0
